Unit_test/__init__.py
Unit_test/test_gpr.py
Unit_test/test_inv.py
Unit_test/test_kernel.py
makeprediction/__init__.py
makeprediction/api.py
makeprediction/exceptions.py
makeprediction/gaussianprocess.py
makeprediction/gpts.py
makeprediction/invtools.py
makeprediction/kernels.py
makeprediction/metrics.py
makeprediction/scores.py
makeprediction/store.py
makeprediction/stream.py
makeprediction/tools.py
makeprediction/version.py
makeprediction/visualization.py
makeprediction_v0/__init__.py
makeprediction_v0/api.py
makeprediction_v0/exceptions.py
makeprediction_v0/gaussianprocess.py
makeprediction_v0/gpts.py
makeprediction_v0/invtools.py
makeprediction_v0/kernels.py
makeprediction_v0/metrics.py
makeprediction_v0/scores.py
makeprediction_v0/store.py
makeprediction_v0/stream.py
makeprediction_v0/tools.py
makeprediction_v0/version.py
makeprediction_v0/visualization.py
makeprediction-4.1.1.dist-info/LICENSE
makeprediction-4.1.1.dist-info/METADATA
makeprediction-4.1.1.dist-info/WHEEL
makeprediction-4.1.1.dist-info/top_level.txt
makeprediction-4.1.1.dist-info/RECORD
