Metadata-Version: 2.1
Name: makeprediction
Version: 4.1.1
Summary: Automatic and fast Gaussian process for time serie prediction.
Home-page: https://github.com/HananyTolba/MakePrediction.git
Download-URL: https://github.com/HananyTolba/MakePrediction.git
Author: Hanany Tolba
Author-email: hananytolba@yahoo.com
License: GPLv3
Keywords: Gaussian Process Regression,Time series prediction,Machine Learning
Classifier: Development Status :: 4 - Beta
Classifier: License :: OSI Approved :: GNU General Public License v3 (GPLv3)
Classifier: Natural Language :: English
Classifier: Operating System :: OS Independent
Classifier: Programming Language :: Python :: 3.6
Classifier: Programming Language :: Python :: 3.7
Classifier: Programming Language :: Python :: 3.8
Classifier: Programming Language :: Python :: 3.9
Classifier: Topic :: Scientific/Engineering :: Artificial Intelligence
Requires-Python: >=3.6
License-File: LICENSE
Requires-Dist: joblib
Requires-Dist: matplotlib
Requires-Dist: numpy
Requires-Dist: pandas
Requires-Dist: plotly
Requires-Dist: pytest
Requires-Dist: requests
Requires-Dist: scipy
Requires-Dist: setuptools
Requires-Dist: tqdm
